<?xml version="1.0" encoding="UTF-8"?>
<!DOCTYPE gdd SYSTEM "gdd.dtd" >

<gdd>

  <package name="PhysEvent">
<!-- ****************************************************************
     * Particle                                                     *
     ****************************************************************-->

    <class
      author="Patrick Koppenburg"
      desc="Physics Analysis Particle. A chosen hypotesis for a possible candidate particle."
      name="Particle"
      stdVectorTypeDef="TRUE"
      id="801"
      >
      <base name="KeyedObject&lt;int&gt;"/>
      &KeyedObject;
      <import name="GaudiKernel/SystemOfUnits.h"/>
      <import name="Event/Vertex" soft="TRUE"/>
      <import name="Event/ProtoParticle" soft="TRUE"/>
      <import name="GaudiKernel/VectorMap"/>
      <import name="GaudiKernel/Point3DTypes.h"/>
      <import name="GaudiKernel/Vector3DTypes.h"/>
      <import name="GaudiKernel/Vector4DTypes.h"/>
      <import name="GaudiKernel/GenericMatrixTypes.h"/>
      <import name="GaudiKernel/SymmetricMatrixTypes.h"/>
      <import name="GaudiKernel/NamedRange"/>
      <import name="GaudiKernel/SharedObjectsContainer"/>
      <import name="Kernel/ParticleID"/>


      <typedef
        type="GaudiUtils::VectorMap&lt;int,double&gt;"
        def="ExtraInfo"
        desc="Vector of information for combined PIDs"
        access="PUBLIC"
        />
      
      <typedef
	  type   = "SharedObjectsContainer&lt;LHCb::Particle&gt;"
	  def    = "Selection"
	  desc   = "The container type for shared particles (without ownership)"
	  access = "PUBLIC"
	  />

      <typedef
	  type   = "Gaudi::NamedRange_&lt;ConstVector&gt;"
	  def    = "Range"
	  desc   = "For uniform access to containers in TES (KeyedContainer,SharedContainer) "
	  access = "PUBLIC"
	  />

      <location
        name="User"
        place="Phys/User/Particles"
        />
     <enum
        desc="Additional information"
        name="additionalInfo"
        access="PUBLIC"
        strTypConv="TRUE">
        <enumval name="Unknown"              value="-1"         desc="Unknown/illegal value of the index for 'additional info'"/>

        <enumval name="ConfLevel"            value="0"          desc="Confidence Level for the particle" />
        <enumval name="Weight"                                  desc="'Weight' for the particle"         />
        <enumval name="Chi2OfMassConstrainedFit"      value="10" desc="Chi2 of Mass Constrained Fit"      />
        <enumval name="Chi2OfDirectionConstrainedFit" value="11" desc="Chi2 of Direction Constrained Fit" />
        <enumval name="Chi2OfVertexConstrainedFit"    value="12" desc="Chi2 of Vertex  Constrained Fit"   />
        <enumval name="Chi2OfParticleReFitter"        value="15" desc="Chi2 From Particle ReFitter"       />
        <enumval name="HasBremAdded"                  value="16" desc="particle momentum is brem-corrected (0/1)"      />
        <enumval name="FlavourTaggingIPPUs"  value="8000"       desc="IPs wrt PU vertices (for FlavourTagging internal use)"   />
        <enumval name="FlavourTaggingTaggerID"  value="8001"    desc="ID of tagger if !=0 (for FlavourTagging internal use)"   />
        <enumval name="Cone1Angle" value="9000"                 desc="Cone angle, cone size 1" />
        <enumval name="Cone1Mult"  value="Cone1Angle+1"         desc="Cone multiplicity, cone size 1" />
        <enumval name="Cone1PX" value="Cone1Angle+2"            desc="Cone Px, cone size 1" />
        <enumval name="Cone1PY" value="Cone1Angle+3"            desc="Cone Py, cone size 1" />
        <enumval name="Cone1PZ" value="Cone1Angle+4"            desc="Cone Pz, cone size 1" />
        <enumval name="Cone1P" value="Cone1Angle+5"             desc="Cone P, cone size 1" />
        <enumval name="Cone1PT" value="Cone1Angle+6"            desc="Cone Pt, cone size 1" />
        <enumval name="Cone1PXAsym" value="Cone1Angle+7"        desc="Cone Px asymmetry, cone size 1" />
        <enumval name="Cone1PYAsym" value="Cone1Angle+8"        desc="Cone Py asymmetry, cone size 1" />
        <enumval name="Cone1PZAsym" value="Cone1Angle+9"        desc="Cone Pz asymmetry, cone size 1" />
        <enumval name="Cone1PAsym" value="Cone1Angle+10"        desc="Cone P asymmetry, cone size 1" />
        <enumval name="Cone1PTAsym" value="Cone1Angle+11"       desc="Cone Pt asymmetry, cone size 1" />
        <enumval name="Cone1DeltaEta" value="Cone1Angle+12"     desc="Cone DeltaEta, cone size 1" />
        <enumval name="Cone1DeltaPhi" value="Cone1Angle+13"     desc="Cone DeltaPhi, cone size 1" />
        <enumval name="Cone2Angle" value="Cone1Angle+14"        desc="Cone angle, cone size 2" />
        <enumval name="Cone2Mult"  value="Cone2Angle+1"         desc="Cone multiplicity, cone size 2" />
        <enumval name="Cone2PX" value="Cone2Angle+2"            desc="Cone Px, cone size 2" />
        <enumval name="Cone2PY" value="Cone2Angle+3"            desc="Cone Py, cone size 2" />
        <enumval name="Cone2PZ" value="Cone2Angle+4"            desc="Cone Pz, cone size 2" />
        <enumval name="Cone2P" value="Cone2Angle+5"             desc="Cone P, cone size 2" />
        <enumval name="Cone2PT" value="Cone2Angle+6"            desc="Cone Pt, cone size 2" />
        <enumval name="Cone2PXAsym" value="Cone2Angle+7"        desc="Cone Px asymmetry, cone size 2" />
        <enumval name="Cone2PYAsym" value="Cone2Angle+8"        desc="Cone Py asymmetry, cone size 2" />
        <enumval name="Cone2PZAsym" value="Cone2Angle+9"        desc="Cone Pz asymmetry, cone size 2" />
        <enumval name="Cone2PAsym" value="Cone2Angle+10"        desc="Cone P asymmetry, cone size 2" />
        <enumval name="Cone2PTAsym" value="Cone2Angle+11"       desc="Cone Pt asymmetry, cone size 2" />
        <enumval name="Cone2DeltaEta" value="Cone2Angle+12"     desc="Cone DeltaEta, cone size 2" />
        <enumval name="Cone2DeltaPhi" value="Cone2Angle+13"     desc="Cone DeltaPhi, cone size 2" />
        <enumval name="Cone3Angle" value="Cone2Angle+14"        desc="Cone angle, cone size 3" />
        <enumval name="Cone3Mult"  value="Cone3Angle+1"         desc="Cone multiplicity, cone size 3" />
        <enumval name="Cone3PX" value="Cone3Angle+2"            desc="Cone Px, cone size 3" />
        <enumval name="Cone3PY" value="Cone3Angle+3"            desc="Cone Py, cone size 3" />
        <enumval name="Cone3PZ" value="Cone3Angle+4"            desc="Cone Pz, cone size 3" />
        <enumval name="Cone3P" value="Cone3Angle+5"             desc="Cone P, cone size 3" />
        <enumval name="Cone3PT" value="Cone3Angle+6"            desc="Cone Pt, cone size 3" />
        <enumval name="Cone3PXAsym" value="Cone3Angle+7"        desc="Cone Px asymmetry, cone size 3" />
        <enumval name="Cone3PYAsym" value="Cone3Angle+8"        desc="Cone Py asymmetry, cone size 3" />
        <enumval name="Cone3PZAsym" value="Cone3Angle+9"        desc="Cone Pz asymmetry, cone size 3" />
        <enumval name="Cone3PAsym" value="Cone3Angle+10"        desc="Cone P asymmetry, cone size 3" />
        <enumval name="Cone3PTAsym" value="Cone3Angle+11"       desc="Cone Pt asymmetry, cone size 3" />
        <enumval name="Cone3DeltaEta" value="Cone3Angle+12"     desc="Cone DeltaEta, cone size 3" />
        <enumval name="Cone3DeltaPhi" value="Cone3Angle+13"     desc="Cone DeltaPhi, cone size 3" />
        <enumval name="Cone4Angle" value="Cone3Angle+14"        desc="Cone angle, cone size 4" />
        <enumval name="Cone4Mult"  value="Cone4Angle+1"         desc="Cone multiplicity, cone size 4" />
        <enumval name="Cone4PX" value="Cone4Angle+2"            desc="Cone Px, cone size 4" />
        <enumval name="Cone4PY" value="Cone4Angle+3"            desc="Cone Py, cone size 4" />
        <enumval name="Cone4PZ" value="Cone4Angle+4"            desc="Cone Pz, cone size 4" />
        <enumval name="Cone4P" value="Cone4Angle+5"             desc="Cone P, cone size 4" />
        <enumval name="Cone4PT" value="Cone4Angle+6"            desc="Cone Pt, cone size 4" />
        <enumval name="Cone4PXAsym" value="Cone4Angle+7"        desc="Cone Px asymmetry, cone size 4" />
        <enumval name="Cone4PYAsym" value="Cone4Angle+8"        desc="Cone Py asymmetry, cone size 4" />
        <enumval name="Cone4PZAsym" value="Cone4Angle+9"        desc="Cone Pz asymmetry, cone size 4" />
        <enumval name="Cone4PAsym" value="Cone4Angle+10"        desc="Cone P asymmetry, cone size 4" />
        <enumval name="Cone4PTAsym" value="Cone4Angle+11"       desc="Cone Pt asymmetry, cone size 4" />
        <enumval name="Cone4DeltaEta" value="Cone4Angle+12"     desc="Cone DeltaEta, cone size 4" />
        <enumval name="Cone4DeltaPhi" value="Cone4Angle+13"     desc="Cone DeltaPhi, cone size 4" />
        <enumval name="EWCone1Index" value="Cone4Angle+14"      desc="First index for EW cone variables, cone size 1" />
        <enumval name="EWCone2Index" value="EWCone1Index+23"    desc="First index for EW cone variables, cone size 2" />
        <enumval name="EWCone3Index" value="EWCone2Index+23"    desc="First index for EW cone variables, cone size 3" />
        <enumval name="EWCone4Index" value="EWCone3Index+23"    desc="First index for EW cone variables, cone size 4" />
        <enumval name="FirstJetIndex"        value="9500"       desc="The first index allocated for jet-related studies"   />
        <enumval name="JetActiveArea"                           desc="Jet Active Area estimation"   />
        <enumval name="JetActiveAreaError"                      desc="Uncertanty in Jet Active Area evaluation"   />
        <enumval name="JetActiveAreaPx"                         desc="Px-component of Jet active area four-momentum"   />
        <enumval name="JetActiveAreaPy"                         desc="Py-component of Jet active area four-momentum"   />
        <enumval name="JetActiveAreaPz"                         desc="Pz-component of Jet active area four-momentum"   />
        <enumval name="JetActiveAreaE"                          desc="E-component  of Jet active area four-momentum"   />
        <enumval name="JetPtPerUnitArea"                        desc="Underlying event activity per unit of Active Area" />
        <enumval name="LastJetIndex"  value="FirstJetIndex+199" desc="The last  index allocated for jet-related studies"   />

        <enumval name="LastGlobal"    value="10000"             desc="The last 'global' index, other values are specific for user analysis" />
      </enum>
      <location
        name="Production"
        place="Phys/Prod/Particles"
        />
      <constructor
        argList="Particle part"
        desc="Copy constructor"
        initList="KeyedObject&lt;int&gt;(), m_particleID( part.m_particleID ), m_measuredMass( part.m_measuredMass ), m_measuredMassErr( part.m_measuredMassErr ), m_momentum( part.m_momentum ), m_referencePoint( part.m_referencePoint ), m_momCovMatrix( part.m_momCovMatrix ), m_posCovMatrix( part.m_posCovMatrix ), m_posMomCovMatrix( part.m_posMomCovMatrix ), m_extraInfo( part.m_extraInfo ), m_endVertex( part.m_endVertex ), m_proto(part.m_proto ), m_daughters( part.m_daughters )"
        />

      <constructor
        explicit = "TRUE"
        argList="const LHCb::ParticleID&amp; pid"
        desc="Constructor from ParticleID"
        initList = "KeyedObject&lt;int&gt;(), m_particleID(pid), m_measuredMass(-1.0), m_measuredMassErr(0.0), m_momentum(0.0, 0.0, 0.0, -1*Gaudi::Units::GeV), m_referencePoint(0.0, 0.0, -100*Gaudi::Units::m), m_momCovMatrix(), m_posCovMatrix(), m_posMomCovMatrix(), m_extraInfo()"
        />

      <constructor
        argList="const LHCb::ParticleID&amp; pid, const int key"
        desc="Constructor from ParticleID and key"
        initList = "KeyedObject&lt;int&gt;(key), m_particleID(pid), m_measuredMass(-1.0), m_measuredMassErr(0.0), m_momentum(0.0, 0.0, 0.0, -1*Gaudi::Units::GeV), m_referencePoint(0.0, 0.0, -100*Gaudi::Units::m), m_momCovMatrix(), m_posCovMatrix(), m_posMomCovMatrix(), m_extraInfo()"
        />

      <method
        name="clone"
        desc="Clone particle"
        type="LHCb::Particle*"
        const="TRUE"
        >
        <code>
          return new Particle(*this);
        </code>
      </method>

      <method
        desc="Assignment operator, note that the original vertex and protoParticle are kept"
        name="operator="
        type="LHCb::Particle&amp;"
        >
        <arg name="rhs" type="Particle" const='TRUE'/>
        <code>
   if ( this != &amp;rhs ) {
      m_particleID      = rhs.m_particleID;
      m_momentum        = rhs.m_momentum;
      m_referencePoint  = rhs.m_referencePoint;
      m_measuredMass    = rhs.m_measuredMass;
      m_measuredMassErr = rhs.m_measuredMassErr;  
      m_posCovMatrix    = rhs.m_posCovMatrix;
      m_momCovMatrix    = rhs.m_momCovMatrix;
      m_posMomCovMatrix = rhs.m_posMomCovMatrix;
      m_extraInfo       = rhs.m_extraInfo;
      m_endVertex       = rhs.m_endVertex;
      m_proto           = rhs.m_proto;
      m_daughters       = rhs.m_daughters;
   }
   return *this;
        </code>
      </method>

      <attribute
        name="particleID"
        desc="PDG code"
        type="LHCb::ParticleID"
        />
      <method
        name="confLevel"
        desc="Confidence Level of the particleID. If not set the default is -1."
        type="double"
        const="TRUE"
        >
        <code>
          return info( LHCb::Particle::ConfLevel, -1. ) ;
        </code>
      </method>
      <method
        name="setConfLevel"
        desc="set confidence Level of the particleID."
        type="void"
	argList="double cl"
        const="FALSE"
        >
        <code>
          addInfo( LHCb::Particle::ConfLevel, cl ) ;
        </code>
      </method>
      <method
        name="weight"
        desc="Weight of the particle, whatever that means. If not set the default is 1."
        type="double"
        const="TRUE"
        >
        <code>
          return info( LHCb::Particle::Weight, 1. ) ;
        </code>
      </method>
      <method
        name="setWeight"
        desc="set Weight of the particle, whatever that means."
        type="void"
	argList="double w"
        const="FALSE"
        >
        <code>
          addInfo( LHCb::Particle::Weight, w ) ;
        </code>
      </method>
      <attribute
        name="measuredMass"
        desc="Measured Mass"
        type="double"
        init="-1.0"
        />
      <attribute
        name="measuredMassErr"
        desc="Error on measured mass"
        type="double"
        init="0.0"
        />
      <attribute
        name="momentum"
        desc="Momentum four vector "
        type="Gaudi::LorentzVector"
        init="0.0, 0.0, 0.0, -1*Gaudi::Units::GeV"
        />
      <attribute
        name="referencePoint"
        desc="Point at which the momentum is given in LHCb reference frame - convention: take the one that minimizes the extrapolations needs"
        type="Gaudi::XYZPoint"
        init="0.0, 0.0, -100*Gaudi::Units::m"
        />
      <relation
        name="endVertex"
        desc="Reference to end vertex (ex. decay)"
        type="LHCb::Vertex"
	nonconstaccessor="TRUE"
        />
      <relation
        name="proto"
        desc="Reference to original ProtoParticle"
        type="LHCb::ProtoParticle"
        />
      <method
        name="charge"
        const="TRUE"
        desc="Charge in units of +e (i.e. electron charge = -1)"
        type="int"
        >
        <code>
          return particleID().threeCharge()/3 ;
        </code>
      </method>
      <method
        name="pt"
        const="TRUE"
        desc="short cut for transerve momentum"
        type="double"
        >
        <code> return m_momentum.Pt(); </code> 
      </method>

      <method
        name="p"
        const="TRUE"
        desc="short cut for |P|" 
        type="double"
        > 
        <code> return m_momentum.R(); </code> 
      </method>
      <method
        const="TRUE"
        name="covMatrix"
        desc="full error matrix on position, 4-momentum. @todo Check the maths of this"
        type="Gaudi::SymMatrix7x7"
	/>

      <attribute
        name="momCovMatrix"
        desc="Covariance matrix relative to momentum (4x4)"
        type="Gaudi::SymMatrix4x4"
        />
      <attribute
        name="posCovMatrix"
        desc="Covariance matrix relative to point at which the momentum is given (3x3)"
        type="Gaudi::SymMatrix3x3"
        />
      <method
        name="isBasicParticle"
	const="TRUE" 
        desc="a basic particle has no daughters" 
        type="bool"
        >
	<code> return m_daughters.empty(); </code>
      </method>
      <attribute
        name="posMomCovMatrix"
        desc="Matrix with correlation errors between momemtum and pointOnTrack (momentum x point)"
        type="Gaudi::Matrix4x3"
        />
      <relation
        name="daughters"
        desc="Reference to daughter particles. Users are strongly discouraged to use setDaughters method." 
        multiplicity="N"
        type="LHCb::Particle"
        />
      <method
        name="daughtersVector"
	desc="Get daughters as a ConstVector"
	type="LHCb::Particle::ConstVector"
	const="TRUE"
	>
	<code>
          return LHCb::Particle::ConstVector( m_daughters.begin(), m_daughters.end() );
	</code>
      </method>
      <attribute
        name="extraInfo"
        desc="Some addtional user information. Don't use directly. Use *Info() methods."
        type="ExtraInfo"
        setMeth="FALSE"
        getMeth="TRUE"
        />
      <method
        name="hasInfo"
        const="TRUE"
        desc="has information for specified key"
        argList="int key"
        type="bool"
        > 
        <code>
          return m_extraInfo.end() != m_extraInfo.find( key ) ;
        </code>
      </method>
      <method
        name="addInfo"
        desc=" add/replace new information, associated with the key"
        argList="int key, double info"
        type="bool"
        > 
        <code>
          return m_extraInfo.insert( key , info ).second ;
        </code>
      </method>
      <method
        name="info"
        desc="extract the information associated with the given key. If there is no such infomration the default value will be returned."
        argList="int key, double def"
        type="double"
        const="TRUE"
        > 
        <code>
          ExtraInfo::const_iterator i = m_extraInfo.find( key ) ;
          return m_extraInfo.end() == i ? def : i->second ;
        </code>
      </method>
      <method
        name="eraseInfo"
        desc="erase the information associated with the given key"
        argList="int key"
        type="unsigned long"
        > 
        <code>
          return m_extraInfo.erase( key ) ; 
        </code>
      </method>

      <method 
        type="Gaudi::XYZVector" 
        name="slopes" 
        const="TRUE" 
        desc="Returns slopes ( Px/Pz, Py/Pz, 1 ) at reference point"
        > 
        <code>
	  return Gaudi::XYZVector( fabs(m_momentum.Z()) > 0 ? m_momentum.X()/m_momentum.Z() : 0 ,
	                           fabs(m_momentum.Z()) > 0 ? m_momentum.Y()/m_momentum.Z() : 0 ,
	                           1.0 );
        </code>
      </method>

      <method 
         name    = "fillStream" 
         desc    = "Print this Particle in a human readable way"
         type    = "std::ostream&amp;" 
         virtual = "FALSE" 
         const   = "TRUE">
         <arg 
           type = "std::ostream" 
           name = "s"/>
      </method>

    </class>
  </package>

</gdd>
