<TaskInventory>
  <NodeList name="HLTE09">
   <Name>HLTE09</Name>
   <Node name="hlte0901"   type="HLTWorker"/>
   <Node name="hlte0902"   type="HLTWorker"/>
   <Node name="hlte0903"   type="HLTWorker"/>
   <Node name="hlte0904"   type="HLTWorker"/>
   <Node name="hlte0905"   type="HLTWorker"/>
   <Node name="hlte0906"   type="HLTWorker"/>
   <Node name="hlte0907"   type="HLTWorker"/>
   <Node name="hlte0908"   type="HLTWorker"/>
   <Node name="hlte0909"   type="HLTWorker"/>
   <Node name="hlte0910"   type="HLTWorker"/>
   <Node name="hlte0911"   type="HLTWorker"/>
   <Node name="hlte09"   type="HLTControl"/>
  </NodeList>
</TaskInventory>

